gifify/__init__.py
gifify/gifify.py
gifify-0.0.6.dist-info/LICENSE
gifify-0.0.6.dist-info/METADATA
gifify-0.0.6.dist-info/WHEEL
gifify-0.0.6.dist-info/top_level.txt
gifify-0.0.6.dist-info/RECORD
