Metadata-Version: 2.1
Name: gifify
Version: 0.0.6
License-File: LICENSE
Requires-Dist: imageio
Requires-Dist: matplotlib
Requires-Dist: ipython
